mtcli_trade/__init__.py
mtcli_trade/commands/__init__.py
mtcli_trade/commands/buy.py
mtcli_trade/commands/cancel.py
mtcli_trade/commands/orders.py
mtcli_trade/commands/positions.py
mtcli_trade/commands/sell.py
mtcli_trade/commands/zera.py
mtcli_trade/conf.py
mtcli_trade/controllers/__init__.py
mtcli_trade/controllers/orders_controller.py
mtcli_trade/models/__init__.py
mtcli_trade/models/ordem_model.py
mtcli_trade/models/orders_model.py
mtcli_trade/models/posicoes_model.py
mtcli_trade/models/risco_model.py
mtcli_trade/plugin.py
mtcli_trade/views/__init__py
mtcli_trade/views/orders_view.py
mtcli_trade-1.6.2.dist-info/entry_points.txt
mtcli_trade-1.6.2.dist-info/LICENSE
mtcli_trade-1.6.2.dist-info/METADATA
mtcli_trade-1.6.2.dist-info/WHEEL
mtcli_trade-1.6.2.dist-info/RECORD
