Metadata-Version: 2.3
Name: mtcli-trade
Version: 1.6.2
Summary: Plugin mtcli para gerenciamento de órdens
License: GPL-3.0
Author: Valmir França da Silva
Author-email: vfranca3@gmail.com
Requires-Python: >=3.10,<3.14.0
Classifier: License :: OSI Approved :: GNU General Public License v3 (GPLv3)
Classifier: Programming Language :: Python :: 3
Classifier: Programming Language :: Python :: 3.10
Classifier: Programming Language :: Python :: 3.11
Classifier: Programming Language :: Python :: 3.12
Classifier: Programming Language :: Python :: 3.13
Requires-Dist: mtcli (>=1.18.1)
Requires-Dist: mtcli-risco (>=2.2.0,<3.0.0)
Project-URL: Documentation, https://mtcli-trade.readthedocs.io
Project-URL: Homepage, https://github.com/vfranca/mtcli-trade
Project-URL: Repository, https://github.com/vfranca/mtcli-trade
Project-URL: issues, https://github.com/vfranca/mtcli-trade/issues
